Metadata-Version: 1.1
Name: stempl
Version: 1.0.7
Summary: HTML templates with just Python
Home-page: http://www.github.com/gabrielhora/stempl
Author: Gabriel Hora
Author-email: gabriel@switchpayments.com
License: MIT
Keywords: html template
Platform: UNKNOWN
Classifier: Development Status :: 5 - Production/Stable
Classifier: Intended Audience :: Developers
Classifier: License :: OSI Approved :: MIT License
Classifier: Programming Language :: Python :: 3
